cosmos_db_wrapper/__init__.py
cosmos_db_wrapper/aio.py
cosmos_db_wrapper/io.py
cosmos_db_wrapper-0.0.14.dist-info/LICENSE
cosmos_db_wrapper-0.0.14.dist-info/METADATA
cosmos_db_wrapper-0.0.14.dist-info/WHEEL
cosmos_db_wrapper-0.0.14.dist-info/top_level.txt
cosmos_db_wrapper-0.0.14.dist-info/RECORD
