Metadata-Version: 2.1
Name: cosmos-db-wrapper
Version: 0.0.14
Summary: Cosmos DB Wrapper: Helper functions to access Microsoft Azure Cosmos DB SQL API
Home-page: https://github.com/spochic/cosmos-db-wrapper
Author: Sebastien Pochic
Author-email: spochic@gmail.com
Project-URL: Bug Tracker, https://github.com/spochic/cosmos-db-wrapper/issues
Classifier: Programming Language :: Python :: 3
Classifier: License :: OSI Approved :: MIT License
Classifier: Operating System :: OS Independent
Classifier: Development Status :: 3 - Alpha
Classifier: Topic :: Database :: Front-Ends
Requires-Python: >=3.10
License-File: LICENSE
